itermate/__init__.py
itermate/operator.py
itermate-1.0.2.dist-info/DESCRIPTION.rst
itermate-1.0.2.dist-info/METADATA
itermate-1.0.2.dist-info/RECORD
itermate-1.0.2.dist-info/WHEEL
itermate-1.0.2.dist-info/metadata.json
itermate-1.0.2.dist-info/top_level.txt
