Metadata-Version: 2.0
Name: itermate
Version: 1.0.2
Summary: Iterator-tools for functional programming.
Home-page: https://github.com/hweickert/itermate
Author: Henry Weickert
Author-email: henryweickert@gmail.com
License: UNKNOWN
Keywords: itermate,itertools,iapply,imapchain
Platform: UNKNOWN
